Workbook
Name Slicer_Age_Group: #N/A
Name Slicer_Category: #N/A
Name Slicer_Country: #N/A
Name Slicer_Gender: #N/A
Name Slicer_Sales_Channel: #N/A

Sheet Dirty_Skincare_Data
A1: Order_ID | B1: Order_Date | C1: Product_ID | D1: Product_Name | E1: Category | F1: Brand | G1: Customer_ID | H1: Gender | I1: Age_Group | J1: Country | K1: Sales_Channel | L1: Quantity_Sold | M1: Cost_Price | N1: Selling_Price | O1: Discount_Percent | P1: Revenue | Q1: Profit | R1: Rating
A2: ORD1121 | B2: Jan 02 2025 | C2: P012 | D2: Sunscreen SPF50 | E2: Protection | F2: GlowBeauty | G2: C232 | H2: Male | I2: Teen | J2: Kenya | K2: Instagram | L2: 2 | M2: 10089 | N2: 12140 | O2: 0.02 | P2: 24280 | Q2: 4102 | R2: 2
A3: ORD1223 | B3: 08/06/2024 | C3: P010 | D3: Hydrating Cream | E3: Moisturizer | G3: C413 | H3: Male | I3: Young Adult | J3: Kenya | K3: WhatsApp | L3: 4 | M3: 13311 | N3: 17701 | O3: 0.04 | P3: 70804 | Q3: 17560 | R3: 3
A4: ORD1222 | B4: 20/07/2024 | C4: P008 | D4: Acne Cleanser | E4: Cleanser | F4: PureSkin | G4: C844 | H4: Female | I4: Adult | J4: nigeria | K4: Instagram | L4: 7 | M4: 3840 | N4: 9112 | O4: 0.1 | P4: 63784 | Q4: 36904 | R4: 4
A5: ORD1029 | B5: 2024-12-25 | C5: P002 | D5: vitamin c serum | E5: Serum | F5: GlowBeauty | G5: C675 | H5: Female | I5: Teen | J5: NIGERIA | K5: Website | L5: 7 | M5: 8462 | N5: 11456 | O5: 0 | P5: 80192 | Q5: 20958 | R5: 4
A6: ORD1039 | B6: Apr 22 2024 | C6: P012 | D6: Sunscreen SPF50 | E6: Protection | F6: GlowBeauty | G6: C156 | H6: Male | I6: Young Adult | J6: Ghana | K6: Retail | L6: 2 | M6: 14499 | N6: 15533 | O6: 0.04 | P6: 31066 | Q6: 2068 | R6: 4
A7: ORD1015 | B7: 2024-12-29 | C7: P014 | D7: Toner | E7: Other | F7: GlowBeauty | G7: C869 | H7: Male | I7: Young Adult | J7: NIGERIA | K7: Instagram | L7: 8 | M7: 6459 | N7: 11182 | O7: 0.04 | P7: 89456 | Q7: 37784 | R7: 4
A8: ORD1142 | B8: Jun 19 2024 | C8: P012 | D8: Sunscreen SPF50 | E8: Protection | F8: PureSkin | G8: C348 | H8: Male | I8: Teen | J8: Ghana | K8: Retail | L8: 2 | M8: 7078 | N8: 11343 | O8: 0.04 | P8: 22686 | Q8: 8530
A9: ORD1155 | B9: 08/03/2025 | C9: P015 | D9: Body Scrub | E9: Other | F9: glowbeauty | G9: C999 | H9: Female | I9: Adult | J9: Nigera | K9: Website | L9: 3 | M9: 14972 | N9: 19467 | O9: 0.04 | P9: 58401 | Q9: 13485 | R9: 5
A10: ORD1058 | B10: 2024-12-25 | C10: P017 | D10: Lip Balm | E10: Other | F10: GlowBeauty | G10: C193 | H10: Female | I10: Adult | J10: Nigera | K10: Instagram | L10: 4 | M10: 6626 | N10: 14222 | O10: 0.02 | P10: 56888 | Q10: 30384 | R10: 2
A11: ORD1201 | B11: Dec 09 2024 | C11: P001 | D11: Vitamin C Serum | E11: Serum | F11: GlowBeauty | G11: C136 | H11: Female | I11: Adult | J11: nigeria | K11: WhatsApp | L11: 2 | M11: 8180 | N11: 13636 | O11: 0.1 | P11: 27272 | Q11: 10912 | R11: 2
A12: ORD1091 | B12: 2025-03-24 | C12: P011 | D12: Night Cream | E12: Moisturizer | F12: PureSkin | G12: C962 | H12: Male | I12: Young Adult | J12: nigeria | K12: WhatsApp | L12: 8 | M12: 5153 | N12: 10367 | O12: 0.1 | P12: 82936 | Q12: 41712 | R12: 4
A13: ORD1064 | B13: Mar 26 2024 | C13: P012 | D13: Sunscreen SPF50 | E13: Protection | F13: SkinLab | G13: C787 | H13: Male | I13: Adult | J13: Ghana | K13: Website | L13: 4 | M13: 8734 | N13: 11969 | O13: 0.02 | P13: 47876 | Q13: 12940 | R13: 3
A14: ORD1062 | B14: Apr 11 2024 | C14: P004 | D14: Niacinamide Serum | E14: Serum | F14: DermaCare | G14: C210 | H14: Female | I14: Teen | J14: Nigera | K14: Retail | L14: 7 | M14: 12972 | N14: 19485 | O14: 0.1 | P14: 136395 | Q14: 45591 | R14: 5
A15: ORD1204 | B15: Oct 04 2024 | C15: P010 | D15: Hydrating Cream | E15: Moisturizer | F15: PureSkin | G15: C562 | H15: Female | I15: Teen | J15: Nigeria | K15: Retail | L15: 5 | M15: 13456 | N15: 15503 | O15: 0.1 | P15: 77515 | Q15: 10235 | R15: 5
A16: ORD1159 | B16: 18/08/2024 | C16: P006 | D16: Face Wash | E16: Cleanser | F16: SkinLab | G16: C341 | H16: Male | I16: Adult | J16: Nigeria | K16: Instagram | L16: 1 | M16: 11846 | N16: 18129 | O16: 0.04 | P16: 18129 | Q16: 6283 | R16: 3
A17: ORD1036 | B17: 14/03/2025 | C17: P014 | D17: Toner | E17: Other | G17: C548 | H17: Male | I17: Young Adult | J17: Kenya | K17: Website | L17: 4 | M17: 8422 | N17: 9879 | O17: 0.02 | P17: 39516 | Q17: 5828 | R17: 5
A18: ORD1209 | B18: 2025-02-22 | C18: P014 | D18: Toner | E18: Other | F18: GlowBeauty | G18: C917 | H18: Female | I18: Teen | J18: Ghana | K18: Website | L18: 2 | M18: 6301 | N18: 11672 | O18: 0.05 | P18: 23344 | Q18: 10742 | R18: 5
A19: ORD1242 | B19: 28/05/2024 | C19: P007 | D19: Deep Clean Cleanser | E19: Cleanser | F19: GlowBeauty | G19: C779 | H19: Female | I19: Young Adult | J19: South Africa | K19: WhatsApp | L19: 3 | M19: 2328 | N19: 8312 | O19: 0.04 | P19: 24936 | Q19: 17952 | R19: 2
A20: ORD1062 | B20: 2024-01-25 | C20: P007 | D20: Deep Clean Cleanser | E20: Cleanser | F20: DermaCare | G20: C661 | H20: Female | I20: Teen | J20: Kenya | K20: Instagram | L20: 4 | M20: 14129 | N20: 20076 | O20: 0.02 | P20: 80304 | Q20: 23788 | R20: 4
A21: ORD1157 | B21: 05/08/2024 | C21: P012 | D21: Sunscreen SPF50 | E21: Protection | F21: DermaCare | G21: C459 | H21: Male | I21: Adult | J21: Ghana | K21: Instagram | L21: 4 | M21: 9490 | N21: 15157 | O21: 0.1 | P21: 60628 | Q21: 22668 | R21: 1
A22: ORD1003 | B22: 24/01/2025 | C22: P012 | D22: Sunscreen SPF50 | E22: Protection | F22: SkinLab | G22: C396 | H22: Female | I22: Adult | J22: Nigera | K22: Website | L22: 8 | M22: 7273 | N22: 9493 | O22: 0.04 | P22: 75944 | Q22: 17760 | R22: 2
A23: ORD1034 | B23: Jan 21 2024 | C23: P018 | D23: Lip Scrub | E23: Other | F23: glowbeauty | G23: C773 | H23: Male | I23: Teen | J23: Kenya | K23: Instagram | L23: 6 | M23: 1818 | N23: 2683 | O23: 0.02 | P23: 16098 | Q23: 5190 | R23: 3
A24: ORD1067 | B24: Apr 29 2025 | C24: P004 | D24: Niacinamide Serum | E24: Serum | F24: SkinLab | G24: C569 | H24: Male | I24: Teen | J24: Nigeria | K24: Website | L24: 1 | M24: 10294 | N24: 14993 | O24: 0.04 | P24: 14993 | Q24: 4699 | R24: 5
A25: ORD1058 | B25: 10/10/2024 | C25: P002 | D25: vitamin c serum | E25: Serum | G25: C921 | H25: Female | I25: Teen | J25: nigeria | K25: WhatsApp | L25: 3 | M25: 14088 | N25: 19941 | O25: 0.1 | P25: 59823 | Q25: 17559
A26: ORD1085 | B26: 17/01/2024 | C26: P005 | D26: Retinol Serum | E26: Serum | F26: DermaCare | G26: C710 | H26: Male | I26: Adult | J26: Nigeria | K26: Instagram | L26: 6 | M26: 14958 | N26: 16291 | O26: 0.1 | P26: 97746 | Q26: 7998 | R26: 2
A27: ORD1143 | B27: 2024-05-22 | C27: P017 | D27: Lip Balm | E27: Other | F27: GlowBeauty | G27: C500 | H27: Female | I27: Adult | J27: NIGERIA | K27: Website | L27: 2 | M27: 1514 | N27: 9203 | O27: 0.1 | P27: 18406 | Q27: 15378 | R27: 4
A28: ORD1049 | B28: 2024-08-03 | C28: P003 | D28: Hyaluronic Acid Serum | E28: Serum | G28: C933 | H28: Male | I28: Teen | J28: nigeria | K28: Instagram | L28: 1 | M28: 14004 | N28: 15696 | O28: 0.04 | P28: 15696 | Q28: 1692 | R28: 4
A29: ORD1050 | B29: 2024-10-28 | C29: P008 | D29: Acne Cleanser | E29: Cleanser | F29: glowbeauty | G29: C695 | H29: Male | I29: Young Adult | J29: nigeria | K29: WhatsApp | L29: 2 | M29: 6906 | N29: 11708 | O29: 0.05 | P29: 23416 | Q29: 9604 | R29: 1
A30: ORD1021 | B30: 2024-08-02 | C30: P003 | D30: Hyaluronic Acid Serum | E30: Serum | F30: GlowBeauty | G30: C455 | H30: Female | I30: Adult | J30: Nigera | K30: Retail | L30: 3 | M30: 10224 | N30: 12730 | O30: 0 | P30: 38190 | Q30: 7518 | R30: 3
A31: ORD1007 | B31: 23/09/2024 | C31: P017 | D31: Lip Balm | E31: Other | F31: PureSkin | G31: C662 | H31: Male | I31: Teen | J31: South Africa | K31: Instagram | L31: 8 | M31: 10339 | N31: 11559 | O31: 0.04 | P31: 92472 | Q31: 9760 | R31: 5
A32: ORD1232 | B32: Nov 14 2024 | C32: P004 | D32: Niacinamide Serum | E32: Serum | G32: C247 | H32: Male | I32: Young Adult | J32: Nigera | K32: Instagram | L32: 6 | M32: 5400 | N32: 13318 | O32: 0.05 | P32: 79908 | Q32: 47508 | R32: 3
A33: ORD1229 | B33: May 06 2024 | C33: P001 | D33: Vitamin C Serum | E33: Serum | F33: GlowBeauty | G33: C303 | H33: Male | I33: Adult | J33: South Africa | K33: Retail | L33: 8 | M33: 11327 | N33: 18223 | O33: 0.05 | P33: 145784 | Q33: 55168 | R33: 1
A34: ORD1205 | B34: 2024-12-08 | C34: P014 | D34: Toner | E34: Other | F34: DermaCare | G34: C405 | H34: Female | I34: Adult | J34: South Africa | K34: WhatsApp | L34: 8 | M34: 13977 | N34: 18293 | O34: 0 | P34: 146344 | Q34: 34528 | R34: 1
A35: ORD1087 | B35: 2024-04-29 | C35: P008 | D35: Acne Cleanser | E35: Cleanser | G35: C791 | H35: Female | I35: Young Adult | J35: Nigeria | K35: Instagram | L35: 4 | M35: 13112 | N35: 13922 | O35: 0.02 | P35: 55688 | Q35: 3240 | R35: 4
A36: ORD1070 | B36: 22/05/2025 | C36: P010 | D36: Hydrating Cream | E36: Moisturizer | F36: DermaCare | G36: C305 | H36: Female | I36: Teen | J36: NIGERIA | K36: Instagram | L36: 5 | M36: 3653 | N36: 6965 | O36: 0.05 | P36: 34825 | Q36: 16560 | R36: 4
A37: ORD1234 | B37: 07/03/2025 | C37: P008 | D37: Acne Cleanser | E37: Cleanser | F37: SkinLab | G37: C970 | H37: Male | I37: Teen | J37: Nigera | K37: WhatsApp | L37: 4 | M37: 1463 | N37: 4907 | O37: 0.02 | P37: 19628 | Q37: 13776 | R37: 2
A38: ORD1142 | B38: 2024-11-10 | C38: P006 | D38: Face Wash | E38: Cleanser | G38: C331 | H38: Male | I38: Young Adult | J38: Nigera | K38: Instagram | L38: 8 | M38: 4947 | N38: 11572 | O38: 0.04 | P38: 92576 | Q38: 53000 | R38: 2
A39: ORD1128 | B39: Feb 21 2024 | C39: P002 | D39: vitamin c serum | E39: Serum | G39: C766 | H39: Male | I39: Teen | J39: Nigera | K39: WhatsApp | L39: 8 | M39: 14145 | N39: 21828 | O39: 0 | P39: 174624 | Q39: 61464 | R39: 3
A40: ORD1128 | B40: 2024-03-24 | C40: P014 | D40: Toner | E40: Other | F40: glowbeauty | G40: C491 | H40: Female | I40: Young Adult | J40: Kenya | K40: Instagram | L40: 4 | M40: 6665 | N40: 12111 | O40: 0 | P40: 48444 | Q40: 21784
A41: ORD1139 | B41: 2024-07-28 | C41: P002 | D41: vitamin c serum | E41: Serum | F41: DermaCare | G41: C271 | H41: Female | I41: Adult | J41: Ghana | K41: Instagram | L41: 8 | M41: 9303 | N41: 16713 | O41: 0.05 | P41: 133704 | Q41: 59280 | R41: 5
A42: ORD1110 | B42: 2024-04-15 | C42: P001 | D42: Vitamin C Serum | E42: Serum | G42: C386 | H42: Female | I42: Adult | J42: Nigeria | K42: Retail | L42: 3 | M42: 10239 | N42: 13735 | O42: 0.02 | P42: 41205 | Q42: 10488 | R42: 3
A43: ORD1012 | B43: Jan 30 2024 | C43: P018 | D43: Lip Scrub | E43: Other | F43: SkinLab | G43: C915 | H43: Female | I43: Adult | J43: nigeria | K43: WhatsApp | L43: 5 | M43: 2729 | N43: 10615 | O43: 0.04 | P43: 53075 | Q43: 39430
A44: ORD1225 | B44: 2024-12-17 | C44: P011 | D44: Night Cream | E44: Moisturizer | F44: SkinLab | G44: C876 | H44: Female | I44: Young Adult | J44: South Africa | K44: Website | L44: 2 | M44: 9127 | N44: 15035 | O44: 0.04 | P44: 30070 | Q44: 11816 | R44: 1
A45: ORD1250 | B45: 05/04/2024 | C45: P015 | D45: Body Scrub | E45: Other | G45: C205 | H45: Male | I45: Adult | J45: Kenya | K45: Retail | L45: 4 | M45: 10622 | N45: 17646 | O45: 0 | P45: 70584 | Q45: 28096
A46: ORD1012 | B46: Mar 17 2024 | C46: P001 | D46: Vitamin C Serum | E46: Serum | F46: DermaCare | G46: C681 | H46: Female | I46: Teen | J46: Nigeria | K46: Instagram | L46: 4 | M46: 7272 | N46: 9025 | O46: 0.04 | P46: 36100 | Q46: 7012 | R46: 5
A47: ORD1083 | B47: 25/05/2025 | C47: P002 | D47: vitamin c serum | E47: Serum | F47: SkinLab | G47: C504 | H47: Female | I47: Adult | J47: Nigeria | K47: Instagram | L47: 8 | M47: 13705 | N47: 17137 | O47: 0 | P47: 137096 | Q47: 27456 | R47: 2
A48: ORD1108 | B48: 05/05/2024 | C48: P011 | D48: Night Cream | E48: Moisturizer | F48: DermaCare | G48: C356 | H48: Male | I48: Young Adult | J48: Ghana | K48: Website | L48: 1 | M48: 14634 | N48: 17402 | O48: 0.04 | P48: 17402 | Q48: 2768
A49: ORD1037 | B49: Sep 27 2024 | C49: P005 | D49: Retinol Serum | E49: Serum | F49: glowbeauty | G49: C448 | H49: Male | I49: Teen | J49: NIGERIA | K49: Instagram | L49: 1 | M49: 5749 | N49: 10658 | O49: 0.05 | P49: 10658 | Q49: 4909 | R49: 2
A50: ORD1062 | B50: Jun 15 2025 | C50: P012 | D50: Sunscreen SPF50 | E50: Protection | G50: C272 | H50: Female | I50: Teen | J50: Ghana | K50: Retail | L50: 8 | M50: 7092 | N50: 9340 | O50: 0 | P50: 74720 | Q50: 17984 | R50: 2
A51: ORD1212 | B51: Feb 04 2025 | C51: P009 | D51: Face Cream | E51: Moisturizer | F51: glowbeauty | G51: C427 | H51: Female | I51: Young Adult | J51: NIGERIA | K51: Website | L51: 2 | M51: 14111 | N51: 16071 | O51: 0.1 | P51: 32142 | Q51: 3920 | R51: 1
A52: ORD1139 | B52: 2024-03-19 | C52: P006 | D52: Face Wash | E52: Cleanser | F52: SkinLab | G52: C222 | H52: Male | I52: Adult | J52: Ghana | K52: WhatsApp | L52: 6 | M52: 12764 | N52: 19047 | O52: 0.04 | P52: 114282 | Q52: 37698 | R52: 4
A53: ORD1187 | B53: 2024-08-11 | C53: P017 | D53: Lip Balm | E53: Other | F53: SkinLab | G53: C725 | H53: Male | I53: Teen | J53: NIGERIA | K53: WhatsApp | L53: 3 | M53: 14260 | N53: 15292 | O53: 0.02 | P53: 45876 | Q53: 3096 | R53: 5
A54: ORD1141 | B54: 02/04/2025 | C54: P012 | D54: Sunscreen SPF50 | E54: Protection | F54: glowbeauty | G54: C890 | H54: Female | I54: Teen | J54: nigeria | K54: WhatsApp | L54: 5 | M54: 9431 | N54: 10935 | O54: 0 | P54: 54675 | Q54: 7520 | R54: 4
A55: ORD1028 | B55: 2024-07-23 | C55: P005 | D55: Retinol Serum | E55: Serum | F55: GlowBeauty | G55: C209 | H55: Male | I55: Teen | J55: NIGERIA | K55: Website | L55: 5 | M55: 4319 | N55: 7297 | O55: 0 | P55: 36485 | Q55: 14890 | R55: 4
A56: ORD1153 | B56: 2024-11-17 | C56: P014 | D56: Toner | E56: Other | F56: glowbeauty | G56: C542 | H56: Male | I56: Young Adult | J56: Nigera | K56: WhatsApp | L56: 4 | M56: 14158 | N56: 15759 | O56: 0 | P56: 63036 | Q56: 6404 | R56: 4
A57: ORD1112 | B57: 10/07/2024 | C57: P010 | D57: Hydrating Cream | E57: Moisturizer | F57: SkinLab | G57: C986 | H57: Female | I57: Young Adult | J57: NIGERIA | K57: WhatsApp | L57: 8 | M57: 11965 | N57: 18639 | O57: 0 | P57: 149112 | Q57: 53392 | R57: 2
A58: ORD1161 | B58: Aug 09 2024 | C58: P011 | D58: Night Cream | E58: Moisturizer | F58: PureSkin | G58: C793 | H58: Male | I58: Teen | J58: South Africa | K58: Retail | L58: 6 | M58: 5848 | N58: 8502 | O58: 0 | P58: 51012 | Q58: 15924
A59: ORD1219 | B59: 16/04/2025 | C59: P013 | D59: Sunscreen SPF30 | E59: Protection | G59: C874 | H59: Female | I59: Teen | J59: NIGERIA | K59: Instagram | L59: 4 | M59: 6585 | N59: 13483 | O59: 0.05 | P59: 53932 | Q59: 27592 | R59: 1
A60: ORD1094 | B60: 2024-03-30 | C60: P005 | D60: Retinol Serum | E60: Serum | F60: SkinLab | G60: C111 | H60: Female | I60: Young Adult | J60: Nigera | K60: WhatsApp | L60: 3 | M60: 7001 | N60: 13035 | O60: 0.02 | P60: 39105 | Q60: 18102 | R60: 3
A61: ORD1099 | B61: 2024-06-14 | C61: P004 | D61: Niacinamide Serum | E61: Serum | F61: PureSkin | G61: C149 | H61: Male | I61: Teen | J61: Nigeria | K61: WhatsApp | L61: 2 | M61: 3057 | N61: 10819 | O61: 0.05 | P61: 21638 | Q61: 15524 | R61: 2
A62: ORD1179 | B62: Mar 01 2025 | C62: P013 | D62: Sunscreen SPF30 | E62: Protection | F62: GlowBeauty | G62: C908 | H62: Female | I62: Young Adult | J62: Kenya | K62: Retail | L62: 5 | M62: 7628 | N62: 15536 | O62: 0.02 | P62: 77680 | Q62: 39540
A63: ORD1033 | B63: 2025-05-24 | C63: P013 | D63: Sunscreen SPF30 | E63: Protection | F63: SkinLab | G63: C487 | H63: Female | I63: Young Adult | J63: nigeria | K63: Instagram | L63: 3 | M63: 1884 | N63: 3634 | O63: 0.04 | P63: 10902 | Q63: 5250 | R63: 3
A64: ORD1107 | B64: 2024-12-16 | C64: P010 | D64: Hydrating Cream | E64: Moisturizer | G64: C682 | H64: Male | I64: Teen | J64: nigeria | K64: Retail | L64: 7 | M64: 13323 | N64: 19796 | O64: 0.05 | P64: 138572 | Q64: 45311 | R64: 4
A65: ORD1073 | B65: 2024-07-04 | C65: P007 | D65: Deep Clean Cleanser | E65: Cleanser | F65: SkinLab | G65: C649 | H65: Male | I65: Young Adult | J65: Nigeria | K65: Website | L65: 4 | M65: 11895 | N65: 19298 | O65: 0.04 | P65: 77192 | Q65: 29612 | R65: 1
A66: ORD1073 | B66: May 09 2025 | C66: P005 | D66: Retinol Serum | E66: Serum | F66: DermaCare | G66: C403 | H66: Male | I66: Teen | J66: Nigera | K66: Retail | L66: 6 | M66: 9388 | N66: 13548 | O66: 0.1 | P66: 81288 | Q66: 24960
A67: ORD1209 | B67: 21/06/2024 | C67: P014 | D67: Toner | E67: Other | F67: GlowBeauty | G67: C661 | H67: Female | I67: Adult | J67: Kenya | K67: Website | L67: 5 | M67: 7284 | N67: 15064 | O67: 0.1 | P67: 75320 | Q67: 38900 | R67: 5
A68: ORD1249 | B68: Jul 04 2024 | C68: P002 | D68: vitamin c serum | E68: Serum | G68: C350 | H68: Female | I68: Teen | J68: Ghana | K68: Retail | L68: 4 | M68: 9238 | N68: 12276 | O68: 0.02 | P68: 49104 | Q68: 12152 | R68: 5
A69: ORD1088 | B69: 2024-09-11 | C69: P003 | D69: Hyaluronic Acid Serum | E69: Serum | F69: SkinLab | G69: C682 | H69: Female | I69: Young Adult | J69: Ghana | K69: Instagram | L69: 1 | M69: 13930 | N69: 16742 | O69: 0.1 | P69: 16742 | Q69: 2812 | R69: 2
A70: ORD1237 | B70: 2024-05-07 | C70: P004 | D70: Niacinamide Serum | E70: Serum | F70: DermaCare | G70: C711 | H70: Female | I70: Adult | J70: Nigera | K70: Website | L70: 2 | M70: 12962 | N70: 16436 | O70: 0.1 | P70: 32872 | Q70: 6948 | R70: 5
A71: ORD1230 | B71: Oct 13 2024 | C71: P017 | D71: Lip Balm | E71: Other | F71: PureSkin | G71: C359 | H71: Female | I71: Teen | J71: Nigeria | K71: Website | L71: 8 | M71: 11628 | N71: 14384 | O71: 0 | P71: 115072 | Q71: 22048 | R71: 1
A72: ORD1041 | B72: 2025-03-09 | C72: P016 | D72: Face Mask | E72: Other | F72: DermaCare | G72: C760 | H72: Female | I72: Adult | J72: Kenya | K72: WhatsApp | L72: 1 | M72: 4458 | N72: 7299 | O72: 0.04 | P72: 7299 | Q72: 2841 | R72: 2
A73: ORD1090 | B73: 2025-04-18 | C73: P007 | D73: Deep Clean Cleanser | E73: Cleanser | F73: GlowBeauty | G73: C422 | H73: Female | I73: Young Adult | J73: nigeria | K73: Retail | L73: 6 | M73: 11375 | N73: 13608 | O73: 0.04 | P73: 81648 | Q73: 13398 | R73: 1
A74: ORD1201 | B74: Apr 22 2024 | C74: P017 | D74: Lip Balm | E74: Other | F74: SkinLab | G74: C553 | H74: Female | I74: Teen | J74: nigeria | K74: WhatsApp | L74: 7 | M74: 8966 | N74: 13879 | O74: 0.02 | P74: 97153 | Q74: 34391 | R74: 3
A75: ORD1197 | B75: Jun 08 2024 | C75: P017 | D75: Lip Balm | E75: Other | G75: C158 | H75: Female | I75: Adult | J75: Ghana | K75: Website | L75: 7 | M75: 11223 | N75: 13773 | O75: 0.05 | P75: 96411 | Q75: 17850 | R75: 5
A76: ORD1173 | B76: 02/06/2024 | C76: P003 | D76: Hyaluronic Acid Serum | E76: Serum | F76: PureSkin | G76: C391 | H76: Male | I76: Teen | J76: South Africa | K76: Retail | L76: 7 | M76: 6664 | N76: 12108 | O76: 0 | P76: 84756 | Q76: 38108 | R76: 3
A77: ORD1128 | B77: 2024-05-06 | C77: P004 | D77: Niacinamide Serum | E77: Serum | G77: C242 | H77: Male | I77: Adult | J77: nigeria | K77: Website | L77: 1 | M77: 8458 | N77: 12863 | O77: 0.04 | P77: 12863 | Q77: 4405 | R77: 4
A78: ORD1059 | B78: Feb 08 2025 | C78: P013 | D78: Sunscreen SPF30 | E78: Protection | F78: SkinLab | G78: C127 | H78: Male | I78: Young Adult | J78: Nigera | K78: Website | L78: 5 | M78: 4045 | N78: 11942 | O78: 0.02 | P78: 59710 | Q78: 39485 | R78: 5
A79: ORD1240 | B79: 09/04/2024 | C79: P003 | D79: Hyaluronic Acid Serum | E79: Serum | F79: GlowBeauty | G79: C753 | H79: Female | I79: Young Adult | J79: NIGERIA | K79: Retail | L79: 3 | M79: 12456 | N79: 13762 | O79: 0.02 | P79: 41286 | Q79: 3918 | R79: 4
A80: ORD1049 | B80: 2024-05-04 | C80: P004 | D80: Niacinamide Serum | E80: Serum | F80: GlowBeauty | G80: C635 | H80: Male | I80: Young Adult | J80: Nigera | K80: WhatsApp | L80: 8 | M80: 14267 | N80: 17723 | O80: 0.1 | P80: 141784 | Q80: 27648 | R80: 4
A81: ORD1224 | B81: 29/03/2025 | C81: P016 | D81: Face Mask | E81: Other | F81: SkinLab | G81: C476 | H81: Female | I81: Adult | J81: Nigeria | K81: WhatsApp | L81: 5 | M81: 1503 | N81: 8771 | O81: 0.05 | P81: 43855 | Q81: 36340 | R81: 2
A82: ORD1110 | B82: Jan 13 2024 | C82: P008 | D82: Acne Cleanser | E82: Cleanser | F82: DermaCare | G82: C930 | H82: Female | I82: Teen | J82: Nigera | K82: Retail | L82: 6 | M82: 3970 | N82: 11831 | O82: 0.1 | P82: 70986 | Q82: 47166 | R82: 4
A83: ORD1029 | B83: 19/11/2024 | C83: P001 | D83: Vitamin C Serum | E83: Serum | F83: GlowBeauty | G83: C762 | H83: Male | I83: Young Adult | J83: Kenya | K83: WhatsApp | L83: 2 | M83: 5157 | N83: 10350 | O83: 0 | P83: 20700 | Q83: 10386 | R83: 2
A84: ORD1110 | B84: 2025-03-24 | C84: P005 | D84: Retinol Serum | E84: Serum | F84: glowbeauty | G84: C561 | H84: Female | I84: Teen | J84: Ghana | K84: Website | L84: 7 | M84: 10591 | N84: 12410 | O84: 0.1 | P84: 86870 | Q84: 12733 | R84: 1
A85: ORD1129 | B85: Mar 01 2024 | C85: P007 | D85: Deep Clean Cleanser | E85: Cleanser | F85: SkinLab | G85: C523 | H85: Male | I85: Young Adult | J85: Nigera | K85: Instagram | L85: 7 | M85: 11418 | N85: 14754 | O85: 0.05 | P85: 103278 | Q85: 23352 | R85: 1
A86: ORD1220 | B86: Jul 11 2024 | C86: P005 | D86: Retinol Serum | E86: Serum | F86: PureSkin | G86: C272 | H86: Female | I86: Teen | J86: NIGERIA | K86: Website | L86: 5 | M86: 8726 | N86: 10177 | O86: 0.02 | P86: 50885 | Q86: 7255 | R86: 1
A87: ORD1116 | B87: 27/01/2024 | C87: P016 | D87: Face Mask | E87: Other | F87: GlowBeauty | G87: C540 | H87: Female | I87: Teen | J87: Kenya | K87: Retail | L87: 4 | M87: 7427 | N87: 10694 | O87: 0.05 | P87: 42776 | Q87: 13068 | R87: 2
A88: ORD1043 | B88: May 14 2025 | C88: P007 | D88: Deep Clean Cleanser | E88: Cleanser | G88: C802 | H88: Male | I88: Young Adult | J88: Nigeria | K88: Instagram | L88: 3 | M88: 7269 | N88: 11885 | O88: 0.02 | P88: 35655 | Q88: 13848 | R88: 1
A89: ORD1193 | B89: 07/08/2024 | C89: P013 | D89: Sunscreen SPF30 | E89: Protection | F89: SkinLab | G89: C322 | H89: Female | I89: Adult | J89: nigeria | K89: Retail | L89: 2 | M89: 7540 | N89: 12287 | O89: 0 | P89: 24574 | Q89: 9494
A90: ORD1043 | B90: 06/11/2024 | C90: P011 | D90: Night Cream | E90: Moisturizer | F90: glowbeauty | G90: C709 | H90: Female | I90: Young Adult | J90: nigeria | K90: Website | L90: 5 | M90: 8710 | N90: 12870 | O90: 0.1 | P90: 64350 | Q90: 20800 | R90: 4
A91: ORD1023 | B91: 2025-04-15 | C91: P013 | D91: Sunscreen SPF30 | E91: Protection | F91: glowbeauty | G91: C448 | H91: Female | I91: Young Adult | J91: Kenya | K91: WhatsApp | L91: 4 | M91: 13084 | N91: 14806 | O91: 0.02 | P91: 59224 | Q91: 6888 | R91: 3
A92: ORD1208 | B92: Oct 03 2024 | C92: P008 | D92: Acne Cleanser | E92: Cleanser | F92: GlowBeauty | G92: C769 | H92: Male | I92: Teen | J92: NIGERIA | K92: Website | L92: 5 | M92: 1946 | N92: 2729 | O92: 0.02 | P92: 13645 | Q92: 3915 | R92: 2
A93: ORD1192 | B93: 13/05/2025 | C93: P003 | D93: Hyaluronic Acid Serum | E93: Serum | F93: GlowBeauty | G93: C644 | H93: Male | I93: Young Adult | J93: Nigeria | K93: Instagram | L93: 1 | M93: 1664 | N93: 5257 | O93: 0.02 | P93: 5257 | Q93: 3593 | R93: 1
A94: ORD1040 | B94: 2024-09-27 | C94: P017 | D94: Lip Balm | E94: Other | F94: PureSkin | G94: C546 | H94: Male | I94: Young Adult | J94: NIGERIA | K94: WhatsApp | L94: 5 | M94: 13181 | N94: 16645 | O94: 0.1 | P94: 83225 | Q94: 17320 | R94: 4
A95: ORD1233 | B95: 14/04/2024 | C95: P003 | D95: Hyaluronic Acid Serum | E95: Serum | F95: glowbeauty | G95: C984 | H95: Male | I95: Teen | J95: Ghana | K95: WhatsApp | L95: 6 | M95: 6038 | N95: 7932 | O95: 0.04 | P95: 47592 | Q95: 11364 | R95: 2
A96: ORD1129 | B96: 2024-07-03 | C96: P012 | D96: Sunscreen SPF50 | E96: Protection | F96: SkinLab | G96: C312 | H96: Male | I96: Teen | J96: Nigera | K96: Website | L96: 2 | M96: 11447 | N96: 14483 | O96: 0.04 | P96: 28966 | Q96: 6072 | R96: 2
A97: ORD1109 | B97: 2024-06-30 | C97: P001 | D97: Vitamin C Serum | E97: Serum | F97: PureSkin | G97: C184 | H97: Male | I97: Teen | J97: Nigeria | K97: Retail | L97: 3 | M97: 12783 | N97: 20529 | O97: 0.02 | P97: 61587 | Q97: 23238 | R97: 4
A98: ORD1004 | B98: 2024-06-26 | C98: P006 | D98: Face Wash | E98: Cleanser | F98: GlowBeauty | G98: C754 | H98: Male | I98: Adult | J98: nigeria | K98: Instagram | L98: 3 | M98: 10854 | N98: 12620 | O98: 0 | P98: 37860 | Q98: 5298 | R98: 3
A99: ORD1224 | B99: 07/06/2025 | C99: P012 | D99: Sunscreen SPF50 | E99: Protection | F99: DermaCare | G99: C602 | H99: Male | I99: Adult | J99: South Africa | K99: Website | L99: 7 | M99: 14299 | N99: 19730 | O99: 0.05 | P99: 138110 | Q99: 38017 | R99: 4
A100: ORD1207 | B100: 2024-11-03 | C100: P010 | D100: Hydrating Cream | E100: Moisturizer | F100: glowbeauty | G100: C988 | H100: Female | I100: Young Adult | J100: Ghana | K100: WhatsApp | L100: 5 | M100: 14267 | N100: 19198 | O100: 0.1 | P100: 95990 | Q100: 24655
...

Sheet Clean_Skincare_Data
A1: Order_ID | B1: Order_Date | C1: Product_ID | D1: Product_Name | E1: Category | F1: Brand | G1: Gender | H1: Age_Group | I1: Country | J1: Sales_Channel | K1: Quantity_Sold | L1: Cost_Price | M1: Total_Cost_Price | N1: Selling_Price | O1: Discount_Percent | P1: Revenue | Q1: Profit | R1: Rating
A2: ORD1001 | B2: 45659 | C2: P012 | D2: Sunscreen Spf50 | E2: Protection | F2: GlowBeauty | G2: Male | H2: Teen | I2: Kenya | J2: Instagram | K2: 2 | L2: 10089 | M2: =Table1[[#This Row],[Cost_Price]]*Table1[[#This Row],[Quantity_Sold]] -> 20178 | N2: 12140 | O2: 0.02 | P2: 24280 | Q2: 4102 | R2: 2
A3: ORD1002 | B3: 45451 | C3: P010 | D3: Hydrating Cream | E3: Moisturizer | F3: N/A | G3: Male | H3: Young Adult | I3: Kenya | J3: WhatsApp | K3: 4 | L3: 13311 | M3: =Table1[[#This Row],[Cost_Price]]*Table1[[#This Row],[Quantity_Sold]] -> 53244 | N3: 17701 | O3: 0.04 | P3: 70804 | Q3: 17560 | R3: 3
A4: ORD1003 | B4: 45493 | C4: P008 | D4: Acne Cleanser | E4: Cleanser | F4: PureSkin | G4: Female | H4: Adult | I4: Nigeria | J4: Instagram | K4: 7 | L4: 3840 | M4: =Table1[[#This Row],[Cost_Price]]*Table1[[#This Row],[Quantity_Sold]] -> 26880 | N4: 9112 | O4: 0.1 | P4: 63784 | Q4: 36904 | R4: 4
A5: ORD1004 | B5: 45651 | C5: P002 | D5: Vitamin C Serum | E5: Serum | F5: GlowBeauty | G5: Female | H5: Teen | I5: Nigeria | J5: Website | K5: 7 | L5: 8462 | M5: =Table1[[#This Row],[Cost_Price]]*Table1[[#This Row],[Quantity_Sold]] -> 59234 | N5: 11456 | O5: 0 | P5: 80192 | Q5: 20958 | R5: 4
A6: ORD1005 | B6: 45404 | C6: P012 | D6: Sunscreen Spf50 | E6: Protection | F6: GlowBeauty | G6: Male | H6: Young Adult | I6: Ghana | J6: Retail | K6: 2 | L6: 14499 | M6: =Table1[[#This Row],[Cost_Price]]*Table1[[#This Row],[Quantity_Sold]] -> 28998 | N6: 15533 | O6: 0.04 | P6: 31066 | Q6: 2068 | R6: 4
A7: ORD1006 | B7: 45655 | C7: P014 | D7: Toner | E7: Other | F7: GlowBeauty | G7: Male | H7: Young Adult | I7: Nigeria | J7: Instagram | K7: 8 | L7: 6459 | M7: =Table1[[#This Row],[Cost_Price]]*Table1[[#This Row],[Quantity_Sold]] -> 51672 | N7: 11182 | O7: 0.04 | P7: 89456 | Q7: 37784 | R7: 4
A8: ORD1007 | B8: 45462 | C8: P012 | D8: Sunscreen Spf50 | E8: Protection | F8: PureSkin | G8: Male | H8: Teen | I8: Ghana | J8: Retail | K8: 2 | L8: 7078 | M8: =Table1[[#This Row],[Cost_Price]]*Table1[[#This Row],[Quantity_Sold]] -> 14156 | N8: 11343 | O8: 0.04 | P8: 22686 | Q8: 8530 | R8: N/A
A9: ORD1008 | B9: 45724 | C9: P015 | D9: Body Scrub | E9: Other | F9: glowbeauty | G9: Female | H9: Adult | I9: Nigeria | J9: Website | K9: 3 | L9: 14972 | M9: =Table1[[#This Row],[Cost_Price]]*Table1[[#This Row],[Quantity_Sold]] -> 44916 | N9: 19467 | O9: 0.04 | P9: 58401 | Q9: 13485 | R9: 5
A10: ORD1009 | B10: 45651 | C10: P017 | D10: Lip Balm | E10: Other | F10: GlowBeauty | G10: Female | H10: Adult | I10: Nigeria | J10: Instagram | K10: 4 | L10: 6626 | M10: =Table1[[#This Row],[Cost_Price]]*Table1[[#This Row],[Quantity_Sold]] -> 26504 | N10: 14222 | O10: 0.02 | P10: 56888 | Q10: 30384 | R10: 2
A11: ORD1010 | B11: 45635 | C11: P001 | D11: Vitamin C Serum | E11: Serum | F11: GlowBeauty | G11: Female | H11: Adult | I11: Nigeria | J11: WhatsApp | K11: 2 | L11: 8180 | M11: =Table1[[#This Row],[Cost_Price]]*Table1[[#This Row],[Quantity_Sold]] -> 16360 | N11: 13636 | O11: 0.1 | P11: 27272 | Q11: 10912 | R11: 2
A12: ORD1011 | B12: 45740 | C12: P011 | D12: Night Cream | E12: Moisturizer | F12: PureSkin | G12: Male | H12: Young Adult | I12: Nigeria | J12: WhatsApp | K12: 8 | L12: 5153 | M12: =Table1[[#This Row],[Cost_Price]]*Table1[[#This Row],[Quantity_Sold]] -> 41224 | N12: 10367 | O12: 0.1 | P12: 82936 | Q12: 41712 | R12: 4
A13: ORD1012 | B13: 45377 | C13: P012 | D13: Sunscreen Spf50 | E13: Protection | F13: SkinLab | G13: Male | H13: Adult | I13: Ghana | J13: Website | K13: 4 | L13: 8734 | M13: =Table1[[#This Row],[Cost_Price]]*Table1[[#This Row],[Quantity_Sold]] -> 34936 | N13: 11969 | O13: 0.02 | P13: 47876 | Q13: 12940 | R13: 3
A14: ORD1013 | B14: 45393 | C14: P004 | D14: Niacinamide Serum | E14: Serum | F14: DermaCare | G14: Female | H14: Teen | I14: Nigeria | J14: Retail | K14: 7 | L14: 12972 | M14: =Table1[[#This Row],[Cost_Price]]*Table1[[#This Row],[Quantity_Sold]] -> 90804 | N14: 19485 | O14: 0.1 | P14: 136395 | Q14: 45591 | R14: 5
A15: ORD1014 | B15: 45569 | C15: P010 | D15: Hydrating Cream | E15: Moisturizer | F15: PureSkin | G15: Female | H15: Teen | I15: Nigeria | J15: Retail | K15: 5 | L15: 13456 | M15: =Table1[[#This Row],[Cost_Price]]*Table1[[#This Row],[Quantity_Sold]] -> 67280 | N15: 15503 | O15: 0.1 | P15: 77515 | Q15: 10235 | R15: 5
A16: ORD1015 | B16: 45522 | C16: P006 | D16: Face Wash | E16: Cleanser | F16: SkinLab | G16: Male | H16: Adult | I16: Nigeria | J16: Instagram | K16: 1 | L16: 11846 | M16: =Table1[[#This Row],[Cost_Price]]*Table1[[#This Row],[Quantity_Sold]] -> 11846 | N16: 18129 | O16: 0.04 | P16: 18129 | Q16: 6283 | R16: 3
A17: ORD1016 | B17: 45730 | C17: P014 | D17: Toner | E17: Other | F17: N/A | G17: Male | H17: Young Adult | I17: Kenya | J17: Website | K17: 4 | L17: 8422 | M17: =Table1[[#This Row],[Cost_Price]]*Table1[[#This Row],[Quantity_Sold]] -> 33688 | N17: 9879 | O17: 0.02 | P17: 39516 | Q17: 5828 | R17: 5
A18: ORD1017 | B18: 45710 | C18: P014 | D18: Toner | E18: Other | F18: GlowBeauty | G18: Female | H18: Teen | I18: Ghana | J18: Website | K18: 2 | L18: 6301 | M18: =Table1[[#This Row],[Cost_Price]]*Table1[[#This Row],[Quantity_Sold]] -> 12602 | N18: 11672 | O18: 0.05 | P18: 23344 | Q18: 10742 | R18: 5
A19: ORD1018 | B19: 45440 | C19: P007 | D19: Deep Clean Cleanser | E19: Cleanser | F19: GlowBeauty | G19: Female | H19: Young Adult | I19: South Africa | J19: WhatsApp | K19: 3 | L19: 2328 | M19: =Table1[[#This Row],[Cost_Price]]*Table1[[#This Row],[Quantity_Sold]] -> 6984 | N19: 8312 | O19: 0.04 | P19: 24936 | Q19: 17952 | R19: 2
A20: ORD1019 | B20: 45316 | C20: P007 | D20: Deep Clean Cleanser | E20: Cleanser | F20: DermaCare | G20: Female | H20: Teen | I20: Kenya | J20: Instagram | K20: 4 | L20: 14129 | M20: =Table1[[#This Row],[Cost_Price]]*Table1[[#This Row],[Quantity_Sold]] -> 56516 | N20: 20076 | O20: 0.02 | P20: 80304 | Q20: 23788 | R20: 4
... A24: ORD1023 | B24: 45776 | C24: P004 | D24: Niacinamide Serum | E24: Serum | F24: SkinLab | G24: Male | H24: Teen | I24: Nigeria | J24: Website | K24: 1 | L24: 10294 | M24: =Table1[[#This Row],[Cost_Price]]*Table1[[#This Row],[Quantity_Sold]] -> 10294 | N24: 14993 | O24: 0.04 | P24: 14993 | Q24: 4699 | R24: 5
A25: ORD1024 | B25: 45575 | C25: P002 | D25: Vitamin C Serum | E25: Serum | F25: N/A | G25: Female | H25: Teen | I25: Nigeria | J25: WhatsApp | K25: 3 | L25: 14088 | M25: =Table1[[#This Row],[Cost_Price]]*Table1[[#This Row],[Quantity_Sold]] -> 42264 | N25: 19941 | O25: 0.1 | P25: 59823 | Q25: 17559 | R25: N/A
A26: ORD1025 | B26: 45308 | C26: P005 | D26: Retinol Serum | E26: Serum | F26: DermaCare | G26: Male | H26: Adult | I26: Nigeria | J26: Instagram | K26: 6 | L26: 14958 | M26: =Table1[[#This Row],[Cost_Price]]*Table1[[#This Row],[Quantity_Sold]] -> 89748 | N26: 16291 | O26: 0.1 | P26: 97746 | Q26: 7998 | R26: 2
A27: ORD1026 | B27: 45434 | C27: P017 | D27: Lip Balm | E27: Other | F27: GlowBeauty | G27: Female | H27: Adult | I27: Nigeria | J27: Website | K27: 2 | L27: 1514 | M27: =Table1[[#This Row],[Cost_Price]]*Table1[[#This Row],[Quantity_Sold]] -> 3028 | N27: 9203 | O27: 0.1 | P27: 18406 | Q27: 15378 | R27: 4
A28: ORD1027 | B28: 45507 | C28: P003 | D28: Hyaluronic Acid Serum | E28: Serum | F28: N/A | G28: Male | H28: Teen | I28: Nigeria | J28: Instagram | K28: 1 | L28: 14004 | M28: =Table1[[#This Row],[Cost_Price]]*Table1[[#This Row],[Quantity_Sold]] -> 14004 | N28: 15696 | O28: 0.04 | P28: 15696 | Q28: 1692 | R28: 4
A29: ORD1028 | B29: 45593 | C29: P008 | D29: Acne Cleanser | E29: Cleanser | F29: glowbeauty | G29: Male | H29: Young Adult | I29: Nigeria | J29: WhatsApp | K29: 2 | L29: 6906 | M29: =Table1[[#This Row],[Cost_Price]]*Table1[[#This Row],[Quantity_Sold]] -> 13812 | N29: 11708 | O29: 0.05 | P29: 23416 | Q29: 9604 | R29: 1
A30: ORD1029 | B30: 45506 | C30: P003 | D30: Hyaluronic Acid Serum | E30: Serum | F30: GlowBeauty | G30: Female | H30: Adult | I30: Nigeria | J30: Retail | K30: 3 | L30: 10224 | M30: =Table1[[#This Row],[Cost_Price]]*Table1[[#This Row],[Quantity_Sold]] -> 30672 | N30: 12730 | O30: 0 | P30: 38190 | Q30: 7518 | R30: 3
A31: ORD1030 | B31: 45558 | C31: P017 | D31: Lip Balm | E31: Other | F31: PureSkin | G31: Male | H31: Teen | I31: South Africa | J31: Instagram | K31: 8 | L31: 10339 | M31: =Table1[[#This Row],[Cost_Price]]*Table1[[#This Row],[Quantity_Sold]] -> 82712 | N31: 11559 | O31: 0.04 | P31: 92472 | Q31: 9760 | R31: 5
A32: ORD1031 | B32: 45610 | C32: P004 | D32: Niacinamide Serum | E32: Serum | F32: N/A | G32: Male | H32: Young Adult | I32: Nigeria | J32: Instagram | K32: 6 | L32: 5400 | M32: =Table1[[#This Row],[Cost_Price]]*Table1[[#This Row],[Quantity_Sold]] -> 32400 | N32: 13318 | O32: 0.05 | P32: 79908 | Q32: 47508 | R32: 3
A33: ORD1032 | B33: 45418 | C33: P001 | D33: Vitamin C Serum | E33: Serum | F33: GlowBeauty | G33: Male | H33: Adult | I33: South Africa | J33: Retail | K33: 8 | L33: 11327 | M33: =Table1[[#This Row],[Cost_Price]]*Table1[[#This Row],[Quantity_Sold]] -> 90616 | N33: 18223 | O33: 0.05 | P33: 145784 | Q33: 55168 | R33: 1
A34: ORD1033 | B34: 45634 | C34: P014 | D34: Toner | E34: Other | F34: DermaCare | G34: Female | H34: Adult | I34: South Africa | J34: WhatsApp | K34: 8 | L34: 13977 | M34: =Table1[[#This Row],[Cost_Price]]*Table1[[#This Row],[Quantity_Sold]] -> 111816 | N34: 18293 | O34: 0 | P34: 146344 | Q34: 34528 | R34: 1
A35: ORD1034 | B35: 45411 | C35: P008 | D35: Acne Cleanser | E35: Cleanser | F35: N/A | G35: Female | H35: Young Adult | I35: Nigeria | J35: Instagram | K35: 4 | L35: 13112 | M35: =Table1[[#This Row],[Cost_Price]]*Table1[[#This Row],[Quantity_Sold]] -> 52448 | N35: 13922 | O35: 0.02 | P35: 55688 | Q35: 3240 | R35: 4
A36: ORD1035 | B36: 45799 | C36: P010 | D36: Hydrating Cream | E36: Moisturizer | F36: DermaCare | G36: Female | H36: Teen | I36: Nigeria | J36: Instagram | K36: 5 | L36: 3653 | M36: =Table1[[#This Row],[Cost_Price]]*Table1[[#This Row],[Quantity_Sold]] -> 18265 | N36: 6965 | O36: 0.05 | P36: 34825 | Q36: 16560 | R36: 4
A37: ORD1036 | B37: 45723 | C37: P008 | D37: Acne Cleanser | E37: Cleanser | F37: SkinLab | G37: Male | H37: Teen | I37: Nigeria | J37: WhatsApp | K37: 4 | L37: 1463 | M37: =Table1[[#This Row],[Cost_Price]]*Table1[[#This Row],[Quantity_Sold]] -> 5852 | N37: 4907 | O37: 0.02 | P37: 19628 | Q37: 13776 | R37: 2
... A39: ORD1038 | B39: 45343 | C39: P002 | D39: Vitamin C Serum | E39: Serum | F39: N/A | G39: Male | H39: Teen | I39: Nigeria | J39: WhatsApp | K39: 8 | L39: 14145 | M39: =Table1[[#This Row],[Cost_Price]]*Table1[[#This Row],[Quantity_Sold]] -> 113160 | N39: 21828 | O39: 0 | P39: 174624 | Q39: 61464 | R39: 3
A40: ORD1039 | B40: 45375 | C40: P014 | D40: Toner | E40: Other | F40: glowbeauty | G40: Female | H40: Young Adult | I40: Kenya | J40: Instagram | K40: 4 | L40: 6665 | M40: =Table1[[#This Row],[Cost_Price]]*Table1[[#This Row],[Quantity_Sold]] -> 26660 | N40: 12111 | O40: 0 | P40: 48444 | Q40: 21784 | R40: N/A
A41: ORD1040 | B41: 45501 | C41: P002 | D41: Vitamin C Serum | E41: Serum | F41: DermaCare | G41: Female | H41: Adult | I41: Ghana | J41: Instagram | K41: 8 | L41: 9303 | M41: =Table1[[#This Row],[Cost_Price]]*Table1[[#This Row],[Quantity_Sold]] -> 74424 | N41: 16713 | O41: 0.05 | P41: 133704 | Q41: 59280 | R41: 5
A42: ORD1041 | B42: 45397 | C42: P001 | D42: Vitamin C Serum | E42: Serum | F42: N/A | G42: Female | H42: Adult | I42: Nigeria | J42: Retail | K42: 3 | L42: 10239 | M42: =Table1[[#This Row],[Cost_Price]]*Table1[[#This Row],[Quantity_Sold]] -> 30717 | N42: 13735 | O42: 0.02 | P42: 41205 | Q42: 10488 | R42: 3
A43: ORD1042 | B43: 45321 | C43: P018 | D43: Lip Scrub | E43: Other | F43: SkinLab | G43: Female | H43: Adult | I43: Nigeria | J43: WhatsApp | K43: 5 | L43: 2729 | M43: =Table1[[#This Row],[Cost_Price]]*Table1[[#This Row],[Quantity_Sold]] -> 13645 | N43: 10615 | O43: 0.04 | P43: 53075 | Q43: 39430 | R43: N/A
A44: ORD1043 | B44: 45643 | C44: P011 | D44: Night Cream | E44: Moisturizer | F44: SkinLab | G44: Female | H44: Young Adult | I44: South Africa | J44: Website | K44: 2 | L44: 9127 | M44: =Table1[[#This Row],[Cost_Price]]*Table1[[#This Row],[Quantity_Sold]] -> 18254 | N44: 15035 | O44: 0.04 | P44: 30070 | Q44: 11816 | R44: 1
A45: ORD1044 | B45: 45387 | C45: P015 | D45: Body Scrub | E45: Other | F45: N/A | G45: Male | H45: Adult | I45: Kenya | J45: Retail | K45: 4 | L45: 10622 | M45: =Table1[[#This Row],[Cost_Price]]*Table1[[#This Row],[Quantity_Sold]] -> 42488 | N45: 17646 | O45: 0 | P45: 70584 | Q45: 28096 | R45: N/A
A46: ORD1045 | B46: 45368 | C46: P001 | D46: Vitamin C Serum | E46: Serum | F46: DermaCare | G46: Female | H46: Teen | I46: Nigeria | J46: Instagram | K46: 4 | L46: 7272 | M46: =Table1[[#This Row],[Cost_Price]]*Table1[[#This Row],[Quantity_Sold]] -> 29088 | N46: 9025 | O46: 0.04 | P46: 36100 | Q46: 7012 | R46: 5
A47: ORD1046 | B47: 45802 | C47: P002 | D47: Vitamin C Serum | E47: Serum | F47: SkinLab | G47: Female | H47: Adult | I47: Nigeria | J47: Instagram | K47: 8 | L47: 13705 | M47: =Table1[[#This Row],[Cost_Price]]*Table1[[#This Row],[Quantity_Sold]] -> 109640 | N47: 17137 | O47: 0 | P47: 137096 | Q47: 27456 | R47: 2
A48: ORD1047 | B48: 45417 | C48: P011 | D48: Night Cream | E48: Moisturizer | F48: DermaCare | G48: Male | H48: Young Adult | I48: Ghana | J48: Website | K48: 1 | L48: 14634 | M48: =Table1[[#This Row],[Cost_Price]]*Table1[[#This Row],[Quantity_Sold]] -> 14634 | N48: 17402 | O48: 0.04 | P48: 17402 | Q48: 2768 | R48: N/A
A49: ORD1048 | B49: 45562 | C49: P005 | D49: Retinol Serum | E49: Serum | F49: glowbeauty | G49: Male | H49: Teen | I49: Nigeria | J49: Instagram | K49: 1 | L49: 5749 | M49: =Table1[[#This Row],[Cost_Price]]*Table1[[#This Row],[Quantity_Sold]] -> 5749 | N49: 10658 | O49: 0.05 | P49: 10658 | Q49: 4909 | R49: 2
A50: ORD1049 | B50: 45823 | C50: P012 | D50: Sunscreen Spf50 | E50: Protection | F50: N/A | G50: Female | H50: Teen | I50: Ghana | J50: Retail | K50: 8 | L50: 7092 | M50: =Table1[[#This Row],[Cost_Price]]*Table1[[#This Row],[Quantity_Sold]] -> 56736 | N50: 9340 | O50: 0 | P50: 74720 | Q50: 17984 | R50: 2
A51: ORD1050 | B51: 45692 | C51: P009 | D51: Face Cream | E51: Moisturizer | F51: glowbeauty | G51: Female | H51: Young Adult | I51: Nigeria | J51: Website | K51: 2 | L51: 14111 | M51: =Table1[[#This Row],[Cost_Price]]*Table1[[#This Row],[Quantity_Sold]] -> 28222 | N51: 16071 | O51: 0.1 | P51: 32142 | Q51: 3920 | R51: 1
A52: ORD1051 | B52: 45370 | C52: P006 | D52: Face Wash | E52: Cleanser | F52: SkinLab | G52: Male | H52: Adult | I52: Ghana | J52: WhatsApp | K52: 6 | L52: 12764 | M52: =Table1[[#This Row],[Cost_Price]]*Table1[[#This Row],[Quantity_Sold]] -> 76584 | N52: 19047 | O52: 0.04 | P52: 114282 | Q52: 37698 | R52: 4
A53: ORD1052 | B53: 45515 | C53: P017 | D53: Lip Balm | E53: Other | F53: SkinLab | G53: Male | H53: Teen | I53: Nigeria | J53: WhatsApp | K53: 3 | L53: 14260 | M53: =Table1[[#This Row],[Cost_Price]]*Table1[[#This Row],[Quantity_Sold]] -> 42780 | N53: 15292 | O53: 0.02 | P53: 45876 | Q53: 3096 | R53: 5
A54: ORD1053 | B54: 45749 | C54: P012 | D54: Sunscreen Spf50 | E54: Protection | F54: glowbeauty | G54: Female | H54: Teen | I54: Nigeria | J54: WhatsApp | K54: 5 | L54: 9431 | M54: =Table1[[#This Row],[Cost_Price]]*Table1[[#This Row],[Quantity_Sold]] -> 47155 | N54: 10935 | O54: 0 | P54: 54675 | Q54: 7520 | R54: 4
A55: ORD1054 | B55: 45496 | C55: P005 | D55: Retinol Serum | E55: Serum | F55: GlowBeauty | G55: Male | H55: Teen | I55: Nigeria | J55: Website | K55: 5 | L55: 4319 | M55: =Table1[[#This Row],[Cost_Price]]*Table1[[#This Row],[Quantity_Sold]] -> 21595 | N55: 7297 | O55: 0 | P55: 36485 | Q55: 14890 | R55: 4
A56: ORD1055 | B56: 45613 | C56: P014 | D56: Toner | E56: Other | F56: glowbeauty | G56: Male | H56: Young Adult | I56: Nigeria | J56: WhatsApp | K56: 4 | L56: 14158 | M56: =Table1[[#This Row],[Cost_Price]]*Table1[[#This Row],[Quantity_Sold]] -> 56632 | N56: 15759 | O56: 0 | P56: 63036 | Q56: 6404 | R56: 4
A57: ORD1056 | B57: 45483 | C57: P010 | D57: Hydrating Cream | E57: Moisturizer | F57: SkinLab | G57: Female | H57: Young Adult | I57: Nigeria | J57: WhatsApp | K57: 8 | L57: 11965 | M57: =Table1[[#This Row],[Cost_Price]]*Table1[[#This Row],[Quantity_Sold]] -> 95720 | N57: 18639 | O57: 0 | P57: 149112 | Q57: 53392 | R57: 2
A58: ORD1057 | B58: 45513 | C58: P011 | D58: Night Cream | E58: Moisturizer | F58: PureSkin | G58: Male | H58: Teen | I58: South Africa | J58: Retail | K58: 6 | L58: 5848 | M58: =Table1[[#This Row],[Cost_Price]]*Table1[[#This Row],[Quantity_Sold]] -> 35088 | N58: 8502 | O58: 0 | P58: 51012 | Q58: 15924 | R58: N/A
A59: ORD1058 | B59: 45763 | C59: P013 | D59: Sunscreen Spf30 | E59: Protection | F59: N/A | G59: Female | H59: Teen | I59: Nigeria | J59: Instagram | K59: 4 | L59: 6585 | M59: =Table1[[#This Row],[Cost_Price]]*Table1[[#This Row],[Quantity_Sold]] -> 26340 | N59: 13483 | O59: 0.05 | P59: 53932 | Q59: 27592 | R59: 1
A60: ORD1059 | B60: 45381 | C60: P005 | D60: Retinol Serum | E60: Serum | F60: SkinLab | G60: Female | H60: Young Adult | I60: Nigeria | J60: WhatsApp | K60: 3 | L60: 7001 | M60: =Table1[[#This Row],[Cost_Price]]*Table1[[#This Row],[Quantity_Sold]] -> 21003 | N60: 13035 | O60: 0.02 | P60: 39105 | Q60: 18102 | R60: 3
A61: ORD1060 | B61: 45457 | C61: P004 | D61: Niacinamide Serum | E61: Serum | F61: PureSkin | G61: Male | H61: Teen | I61: Nigeria | J61: WhatsApp | K61: 2 | L61: 3057 | M61: =Table1[[#This Row],[Cost_Price]]*Table1[[#This Row],[Quantity_Sold]] -> 6114 | N61: 10819 | O61: 0.05 | P61: 21638 | Q61: 15524 | R61: 2
A62: ORD1061 | B62: 45717 | C62: P013 | D62: Sunscreen Spf30 | E62: Protection | F62: GlowBeauty | G62: Female | H62: Young Adult | I62: Kenya | J62: Retail | K62: 5 | L62: 7628 | M62: =Table1[[#This Row],[Cost_Price]]*Table1[[#This Row],[Quantity_Sold]] -> 38140 | N62: 15536 | O62: 0.02 | P62: 77680 | Q62: 39540 | R62: N/A
A63: ORD1062 | B63: 45801 | C63: P013 | D63: Sunscreen Spf30 | E63: Protection | F63: SkinLab | G63: Female | H63: Young Adult | I63: Nigeria | J63: Instagram | K63: 3 | L63: 1884 | M63: =Table1[[#This Row],[Cost_Price]]*Table1[[#This Row],[Quantity_Sold]] -> 5652 | N63: 3634 | O63: 0.04 | P63: 10902 | Q63: 5250 | R63: 3
A64: ORD1063 | B64: 45642 | C64: P010 | D64: Hydrating Cream | E64: Moisturizer | F64: N/A | G64: Male | H64: Teen | I64: Nigeria | J64: Retail | K64: 7 | L64: 13323 | M64: =Table1[[#This Row],[Cost_Price]]*Table1[[#This Row],[Quantity_Sold]] -> 93261 | N64: 19796 | O64: 0.05 | P64: 138572 | Q64: 45311 | R64: 4
A65: ORD1064 | B65: 45477 | C65: P007 | D65: Deep Clean Cleanser | E65: Cleanser | F65: SkinLab | G65: Male | H65: Young Adult | I65: Nigeria | J65: Website | K65: 4 | L65: 11895 | M65: =Table1[[#This Row],[Cost_Price]]*Table1[[#This Row],[Quantity_Sold]] -> 47580 | N65: 19298 | O65: 0.04 | P65: 77192 | Q65: 29612 | R65: 1
A66: ORD1065 | B66: 45786 | C66: P005 | D66: Retinol Serum | E66: Serum | F66: DermaCare | G66: Male | H66: Teen | I66: Nigeria | J66: Retail | K66: 6 | L66: 9388 | M66: =Table1[[#This Row],[Cost_Price]]*Table1[[#This Row],[Quantity_Sold]] -> 56328 | N66: 13548 | O66: 0.1 | P66: 81288 | Q66: 24960 | R66: N/A
A67: ORD1066 | B67: 45464 | C67: P014 | D67: Toner | E67: Other | F67: GlowBeauty | G67: Female | H67: Adult | I67: Kenya | J67: Website | K67: 5 | L67: 7284 | M67: =Table1[[#This Row],[Cost_Price]]*Table1[[#This Row],[Quantity_Sold]] -> 36420 | N67: 15064 | O67: 0.1 | P67: 75320 | Q67: 38900 | R67: 5
A68: ORD1067 | B68: 45477 | C68: P002 | D68: Vitamin C Serum | E68: Serum | F68: N/A | G68: Female | H68: Teen | I68: Ghana | J68: Retail | K68: 4 | L68: 9238 | M68: =Table1[[#This Row],[Cost_Price]]*Table1[[#This Row],[Quantity_Sold]] -> 36952 | N68: 12276 | O68: 0.02 | P68: 49104 | Q68: 12152 | R68: 5
A69: ORD1068 | B69: 45546 | C69: P003 | D69: Hyaluronic Acid Serum | E69: Serum | F69: SkinLab | G69: Female | H69: Young Adult | I69: Ghana | J69: Instagram | K69: 1 | L69: 13930 | M69: =Table1[[#This Row],[Cost_Price]]*Table1[[#This Row],[Quantity_Sold]] -> 13930 | N69: 16742 | O69: 0.1 | P69: 16742 | Q69: 2812 | R69: 2
A70: ORD1069 | B70: 45419 | C70: P004 | D70: Niacinamide Serum | E70: Serum | F70: DermaCare | G70: Female | H70: Adult | I70: Nigeria | J70: Website | K70: 2 | L70: 12962 | M70: =Table1[[#This Row],[Cost_Price]]*Table1[[#This Row],[Quantity_Sold]] -> 25924 | N70: 16436 | O70: 0.1 | P70: 32872 | Q70: 6948 | R70: 5
A71: ORD1070 | B71: 45578 | C71: P017 | D71: Lip Balm | E71: Other | F71: PureSkin | G71: Female | H71: Teen | I71: Nigeria | J71: Website | K71: 8 | L71: 11628 | M71: =Table1[[#This Row],[Cost_Price]]*Table1[[#This Row],[Quantity_Sold]] -> 93024 | N71: 14384 | O71: 0 | P71: 115072 | Q71: 22048 | R71: 1
A72: ORD1071 | B72: 45725 | C72: P016 | D72: Face Mask | E72: Other | F72: DermaCare | G72: Female | H72: Adult | I72: Kenya | J72: WhatsApp | K72: 1 | L72: 4458 | M72: =Table1[[#This Row],[Cost_Price]]*Table1[[#This Row],[Quantity_Sold]] -> 4458 | N72: 7299 | O72: 0.04 | P72: 7299 | Q72: 2841 | R72: 2
A73: ORD1072 | B73: 45765 | C73: P007 | D73: Deep Clean Cleanser | E73: Cleanser | F73: GlowBeauty | G73: Female | H73: Young Adult | I73: Nigeria | J73: Retail | K73: 6 | L73: 11375 | M73: =Table1[[#This Row],[Cost_Price]]*Table1[[#This Row],[Quantity_Sold]] -> 68250 | N73: 13608 | O73: 0.04 | P73: 81648 | Q73: 13398 | R73: 1
A74: ORD1073 | B74: 45404 | C74: P017 | D74: Lip Balm | E74: Other | F74: SkinLab | G74: Female | H74: Teen | I74: Nigeria | J74: WhatsApp | K74: 7 | L74: 8966 | M74: =Table1[[#This Row],[Cost_Price]]*Table1[[#This Row],[Quantity_Sold]] -> 62762 | N74: 13879 | O74: 0.02 | P74: 97153 | Q74: 34391 | R74: 3
A75: ORD1074 | B75: 45451 | C75: P017 | D75: Lip Balm | E75: Other | F75: N/A | G75: Female | H75: Adult | I75: Ghana | J75: Website | K75: 7 | L75: 11223 | M75: =Table1[[#This Row],[Cost_Price]]*Table1[[#This Row],[Quantity_Sold]] -> 78561 | N75: 13773 | O75: 0.05 | P75: 96411 | Q75: 17850 | R75: 5
A76: ORD1075 | B76: 45445 | C76: P003 | D76: Hyaluronic Acid Serum | E76: Serum | F76: PureSkin | G76: Male | H76: Teen | I76: South Africa | J76: Retail | K76: 7 | L76: 6664 | M76: =Table1[[#This Row],[Cost_Price]]*Table1[[#This Row],[Quantity_Sold]] -> 46648 | N76: 12108 | O76: 0 | P76: 84756 | Q76: 38108 | R76: 3
A77: ORD1076 | B77: 45418 | C77: P004 | D77: Niacinamide Serum | E77: Serum | F77: N/A | G77: Male | H77: Adult | I77: Nigeria | J77: Website | K77: 1 | L77: 8458 | M77: =Table1[[#This Row],[Cost_Price]]*Table1[[#This Row],[Quantity_Sold]] -> 8458 | N77: 12863 | O77: 0.04 | P77: 12863 | Q77: 4405 | R77: 4
A78: ORD1077 | B78: 45696 | C78: P013 | D78: Sunscreen Spf30 | E78: Protection | F78: SkinLab | G78: Male | H78: Young Adult | I78: Nigeria | J78: Website | K78: 5 | L78: 4045 | M78: =Table1[[#This Row],[Cost_Price]]*Table1[[#This Row],[Quantity_Sold]] -> 20225 | N78: 11942 | O78: 0.02 | P78: 59710 | Q78: 39485 | R78: 5
... A88: ORD1087 | B88: 45791 | C88: P007 | D88: Deep Clean Cleanser | E88: Cleanser | F88: N/A | G88: Male | H88: Young Adult | I88: Nigeria | J88: Instagram | K88: 3 | L88: 7269 | M88: =Table1[[#This Row],[Cost_Price]]*Table1[[#This Row],[Quantity_Sold]] -> 21807 | N88: 11885 | O88: 0.02 | P88: 35655 | Q88: 13848 | R88: 1
A89: ORD1088 | B89: 45511 | C89: P013 | D89: Sunscreen Spf30 | E89: Protection | F89: SkinLab | G89: Female | H89: Adult | I89: Nigeria | J89: Retail | K89: 2 | L89: 7540 | M89: =Table1[[#This Row],[Cost_Price]]*Table1[[#This Row],[Quantity_Sold]] -> 15080 | N89: 12287 | O89: 0 | P89: 24574 | Q89: 9494 | R89: N/A
A90: ORD1089 | B90: 45602 | C90: P011 | D90: Night Cream | E90: Moisturizer | F90: glowbeauty | G90: Female | H90: Young Adult | I90: Nigeria | J90: Website | K90: 5 | L90: 8710 | M90: =Table1[[#This Row],[Cost_Price]]*Table1[[#This Row],[Quantity_Sold]] -> 43550 | N90: 12870 | O90: 0.1 | P90: 64350 | Q90: 20800 | R90: 4
A91: ORD1090 | B91: 45762 | C91: P013 | D91: Sunscreen Spf30 | E91: Protection | F91: glowbeauty | G91: Female | H91: Young Adult | I91: Kenya | J91: WhatsApp | K91: 4 | L91: 13084 | M91: =Table1[[#This Row],[Cost_Price]]*Table1[[#This Row],[Quantity_Sold]] -> 52336 | N91: 14806 | O91: 0.02 | P91: 59224 | Q91: 6888 | R91: 3
A92: ORD1091 | B92: 45568 | C92: P008 | D92: Acne Cleanser | E92: Cleanser | F92: GlowBeauty | G92: Male | H92: Teen | I92: Nigeria | J92: Website | K92: 5 | L92: 1946 | M92: =Table1[[#This Row],[Cost_Price]]*Table1[[#This Row],[Quantity_Sold]] -> 9730 | N92: 2729 | O92: 0.02 | P92: 13645 | Q92: 3915 | R92: 2
A93: ORD1092 | B93: 45790 | C93: P003 | D93: Hyaluronic Acid Serum | E93: Serum | F93: GlowBeauty | G93: Male | H93: Young Adult | I93: Nigeria | J93: Instagram | K93: 1 | L93: 1664 | M93: =Table1[[#This Row],[Cost_Price]]*Table1[[#This Row],[Quantity_Sold]] -> 1664 | N93: 5257 | O93: 0.02 | P93: 5257 | Q93: 3593 | R93: 1
A94: ORD1093 | B94: 45562 | C94: P017 | D94: Lip Balm | E94: Other | F94: PureSkin | G94: Male | H94: Young Adult | I94: Nigeria | J94: WhatsApp | K94: 5 | L94: 13181 | M94: =Table1[[#This Row],[Cost_Price]]*Table1[[#This Row],[Quantity_Sold]] -> 65905 | N94: 16645 | O94: 0.1 | P94: 83225 | Q94: 17320 | R94: 4
A95: ORD1094 | B95: 45396 | C95: P003 | D95: Hyaluronic Acid Serum | E95: Serum | F95: glowbeauty | G95: Male | H95: Teen | I95: Ghana | J95: WhatsApp | K95: 6 | L95: 6038 | M95: =Table1[[#This Row],[Cost_Price]]*Table1[[#This Row],[Quantity_Sold]] -> 36228 | N95: 7932 | O95: 0.04 | P95: 47592 | Q95: 11364 | R95: 2
A96: ORD1095 | B96: 45476 | C96: P012 | D96: Sunscreen Spf50 | E96: Protection | F96: SkinLab | G96: Male | H96: Teen | I96: Nigeria | J96: Website | K96: 2 | L96: 11447 | M96: =Table1[[#This Row],[Cost_Price]]*Table1[[#This Row],[Quantity_Sold]] -> 22894 | N96: 14483 | O96: 0.04 | P96: 28966 | Q96: 6072 | R96: 2
A97: ORD1096 | B97: 45473 | C97: P001 | D97: Vitamin C Serum | E97: Serum | F97: PureSkin | G97: Male | H97: Teen | I97: Nigeria | J97: Retail | K97: 3 | L97: 12783 | M97: =Table1[[#This Row],[Cost_Price]]*Table1[[#This Row],[Quantity_Sold]] -> 38349 | N97: 20529 | O97: 0.02 | P97: 61587 | Q97: 23238 | R97: 4
A98: ORD1097 | B98: 45469 | C98: P006 | D98: Face Wash | E98: Cleanser | F98: GlowBeauty | G98: Male | H98: Adult | I98: Nigeria | J98: Instagram | K98: 3 | L98: 10854 | M98: =Table1[[#This Row],[Cost_Price]]*Table1[[#This Row],[Quantity_Sold]] -> 32562 | N98: 12620 | O98: 0 | P98: 37860 | Q98: 5298 | R98: 3
A99: ORD1098 | B99: 45815 | C99: P012 | D99: Sunscreen Spf50 | E99: Protection | F99: DermaCare | G99: Male | H99: Adult | I99: South Africa | J99: Website | K99: 7 | L99: 14299 | M99: =Table1[[#This Row],[Cost_Price]]*Table1[[#This Row],[Quantity_Sold]] -> 100093 | N99: 19730 | O99: 0.05 | P99: 138110 | Q99: 38017 | R99: 4
A100: ORD1099 | B100: 45599 | C100: P010 | D100: Hydrating Cream | E100: Moisturizer | F100: glowbeauty | G100: Female | H100: Young Adult | I100: Ghana | J100: WhatsApp | K100: 5 | L100: 14267 | M100: =Table1[[#This Row],[Cost_Price]]*Table1[[#This Row],[Quantity_Sold]] -> 71335 | N100: 19198 | O100: 0.1 | P100: 95990 | Q100: 24655 | R100: N/A
A101: ORD1100 | B101: 45608 | C101: P015 | D101: Body Scrub | E101: Other | F101: PureSkin | G101: Male | H101: Young Adult | I101: Kenya | J101: Retail | K101: 7 | L101: 14806 | M101: =Table1[[#This Row],[Cost_Price]]*Table1[[#This Row],[Quantity_Sold]] -> 103642 | N101: 18873 | O101: 0.1 | P101: 132111 | Q101: 28469 | R101: 5
A102: ORD1101 | B102: 45473 | C102: P001 | D102: Vitamin C Serum | E102: Serum | F102: glowbeauty | G102: Female | H102: Teen | I102: Kenya | J102: Instagram | K102: 7 | L102: 14868 | M102: =Table1[[#This Row],[Cost_Price]]*Table1[[#This Row],[Quantity_Sold]] -> 104076 | N102: 22024 | O102: 0.05 | P102: 154168 | Q102: 50092 | R102: 2
A103: ORD1102 | B103: 45343 | C103: P009 | D103: Face Cream | E103: Moisturizer | F103: PureSkin | G103: Female | H103: Teen | I103: Ghana | J103: WhatsApp | K103: 2 | L103: 7457 | M103: =Table1[[#This Row],[Cost_Price]]*Table1[[#This Row],[Quantity_Sold]] -> 14914 | N103: 11534 | O103: 0.02 | P103: 23068 | Q103: 8154 | R103: 1
A104: ORD1103 | B104: 45473 | C104: P018 | D104: Lip Scrub | E104: Other | F104: glowbeauty | G104: Female | H104: Adult | I104: Nigeria | J104: Instagram | K104: 3 | L104: 3471 | M104: =Table1[[#This Row],[Cost_Price]]*Table1[[#This Row],[Quantity_Sold]] -> 10413 | N104: 9502 | O104: 0.04 | P104: 28506 | Q104: 18093 | R104: 1
A105: ORD1104 | B105: 45639 | C105: P003 | D105: Hyaluronic Acid Serum | E105: Serum | F105: SkinLab | G105: Male | H105: Young Adult | I105: Ghana | J105: Instagram | K105: 4 | L105: 5450 | M105: =Table1[[#This Row],[Cost_Price]]*Table1[[#This Row],[Quantity_Sold]] -> 21800 | N105: 9306 | O105: 0.05 | P105: 37224 | Q105: 15424 | R105: 2
A106: ORD1105 | B106: 45485 | C106: P018 | D106: Lip Scrub | E106: Other | F106: PureSkin | G106: Male | H106: Adult | I106: Nigeria | J106: Instagram | K106: 4 | L106: 2709 | M106: =Table1[[#This Row],[Cost_Price]]*Table1[[#This Row],[Quantity_Sold]] -> 10836 | N106: 6187 | O106: 0.02 | P106: 24748 | Q106: 13912 | R106: 5
A107: ORD1106 | B107: 45383 | C107: P009 | D107: Face Cream | E107: Moisturizer | F107: glowbeauty | G107: Male | H107: Young Adult | I107: Nigeria | J107: Retail | K107: 2 | L107: 11787 | M107: =Table1[[#This Row],[Cost_Price]]*Table1[[#This Row],[Quantity_Sold]] -> 23574 | N107: 18021 | O107: 0.04 | P107: 36042 | Q107: 12468 | R107: 2
A108: ORD1107 | B108: 45555 | C108: P003 | D108: Hyaluronic Acid Serum | E108: Serum | F108: GlowBeauty | G108: Female | H108: Teen | I108: Kenya | J108: Retail | K108: 3 | L108: 3257 | M108: =Table1[[#This Row],[Cost_Price]]*Table1[[#This Row],[Quantity_Sold]] -> 9771 | N108: 9132 | O108: 0.1 | P108: 27396 | Q108: 17625 | R108: 5
A109: ORD1108 | B109: 45313 | C109: P016 | D109: Face Mask | E109: Other | F109: N/A | G109: Male | H109: Young Adult | I109: Nigeria | J109: WhatsApp | K109: 2 | L109: 6340 | M109: =Table1[[#This Row],[Cost_Price]]*Table1[[#This Row],[Quantity_Sold]] -> 12680 | N109: 13483 | O109: 0.04 | P109: 26966 | Q109: 14286 | R109: 2
A110: ORD1109 | B110: 45433 | C110: P005 | D110: Retinol Serum | E110: Serum | F110: SkinLab | G110: Female | H110: Young Adult | I110: Kenya | J110: WhatsApp | K110: 3 | L110: 2076 | M110: =Table1[[#This Row],[Cost_Price]]*Table1[[#This Row],[Quantity_Sold]] -> 6228 | N110: 3914 | O110: 0 | P110: 11742 | Q110: 5514 | R110: 5
A111: ORD1110 | B111: 45772 | C111: P014 | D111: Toner | E111: Other | F111: N/A | G111: Male | H111: Young Adult | I111: Nigeria | J111: Retail | K111: 5 | L111: 3104 | M111: =Table1[[#This Row],[Cost_Price]]*Table1[[#This Row],[Quantity_Sold]] -> 15520 | N111: 5764 | O111: 0.04 | P111: 28820 | Q111: 13300 | R111: 2
A112: ORD1111 | B112: 45517 | C112: P009 | D112: Face Cream | E112: Moisturizer | F112: DermaCare | G112: Female | H112: Young Adult | I112: Nigeria | J112: Website | K112: 4 | L112: 10338 | M112: =Table1[[#This Row],[Cost_Price]]*Table1[[#This Row],[Quantity_Sold]] -> 41352 | N112: 16436 | O112: 0.1 | P112: 65744 | Q112: 24392 | R112: 3
A113: ORD1112 | B113: 45473 | C113: P017 | D113: Lip Balm | E113: Other | F113: GlowBeauty | G113: Male | H113: Adult | I113: Nigeria | J113: Instagram | K113: 2 | L113: 11920 | M113: =Table1[[#This Row],[Cost_Price]]*Table1[[#This Row],[Quantity_Sold]] -> 23840 | N113: 17014 | O113: 0.1 | P113: 34028 | Q113: 10188 | R113: 5
...

Sheet Product_Master
A1: Product_Name | B1: Avg_Cost_Price | C1: Avg_Selling_Price
A2: Sunscreen Spf50 | B2: =AVERAGEIFS(Clean_Skincare_Data!L:L, Clean_Skincare_Data!D:D, A2) -> 8386.7941 | C2: =AVERAGEIFS(Clean_Skincare_Data!N:N, Clean_Skincare_Data!D:D, A2) -> 12079.118
A3: Hydrating Cream | B3: =AVERAGEIFS(Clean_Skincare_Data!L:L, Clean_Skincare_Data!D:D, A3) -> 7565.9667 | C3: =AVERAGEIFS(Clean_Skincare_Data!N:N, Clean_Skincare_Data!D:D, A3) -> 12551.267
A4: Acne Cleanser | B4: =AVERAGEIFS(Clean_Skincare_Data!L:L, Clean_Skincare_Data!D:D, A4) -> 8217.625 | C4: =AVERAGEIFS(Clean_Skincare_Data!N:N, Clean_Skincare_Data!D:D, A4) -> 12092.5
A5: Vitamin C Serum | B5: =AVERAGEIFS(Clean_Skincare_Data!L:L, Clean_Skincare_Data!D:D, A5) -> 9404.2712 | C5: =AVERAGEIFS(Clean_Skincare_Data!N:N, Clean_Skincare_Data!D:D, A5) -> 14208.203
A6: Toner | B6: =AVERAGEIFS(Clean_Skincare_Data!L:L, Clean_Skincare_Data!D:D, A6) -> 9057 | C6: =AVERAGEIFS(Clean_Skincare_Data!N:N, Clean_Skincare_Data!D:D, A6) -> 12823.5
A7: Body Scrub | B7: =AVERAGEIFS(Clean_Skincare_Data!L:L, Clean_Skincare_Data!D:D, A7) -> 9310.8182 | C7: =AVERAGEIFS(Clean_Skincare_Data!N:N, Clean_Skincare_Data!D:D, A7) -> 13533.303
A8: Lip Balm | B8: =AVERAGEIFS(Clean_Skincare_Data!L:L, Clean_Skincare_Data!D:D, A8) -> 7710.5938 | C8: =AVERAGEIFS(Clean_Skincare_Data!N:N, Clean_Skincare_Data!D:D, A8) -> 11801.438
A9: Night Cream | B9: =AVERAGEIFS(Clean_Skincare_Data!L:L, Clean_Skincare_Data!D:D, A9) -> 7888.28 | C9: =AVERAGEIFS(Clean_Skincare_Data!N:N, Clean_Skincare_Data!D:D, A9) -> 12213.4
A10: Niacinamide Serum | B10: =AVERAGEIFS(Clean_Skincare_Data!L:L, Clean_Skincare_Data!D:D, A10) -> 8522 | C10: =AVERAGEIFS(Clean_Skincare_Data!N:N, Clean_Skincare_Data!D:D, A10) -> 12766.28
A11: Face Wash | B11: =AVERAGEIFS(Clean_Skincare_Data!L:L, Clean_Skincare_Data!D:D, A11) -> 6827.64 | C11: =AVERAGEIFS(Clean_Skincare_Data!N:N, Clean_Skincare_Data!D:D, A11) -> 11481.64
A12: Deep Clean Cleanser | B12: =AVERAGEIFS(Clean_Skincare_Data!L:L, Clean_Skincare_Data!D:D, A12) -> 8321.875 | C12: =AVERAGEIFS(Clean_Skincare_Data!N:N, Clean_Skincare_Data!D:D, A12) -> 12728.833
A13: Lip Scrub | B13: =AVERAGEIFS(Clean_Skincare_Data!L:L, Clean_Skincare_Data!D:D, A13) -> 8220.7857 | C13: =AVERAGEIFS(Clean_Skincare_Data!N:N, Clean_Skincare_Data!D:D, A13) -> 13188.536
... A18: Face Mask | B18: =AVERAGEIFS(Clean_Skincare_Data!L:L, Clean_Skincare_Data!D:D, A18) -> 7073.6087 | C18: =AVERAGEIFS(Clean_Skincare_Data!N:N, Clean_Skincare_Data!D:D, A18) -> 11118.696

Sheet Discount_Calculator
A1: SKINCARE DISCOUNT & PROFIT CALCULATOR
A2: Product Name | B2: Hydrating Cream
A3: Avg Cost Price | B3: =_xlfn.XLOOKUP(B2, Product_Master!A:A, Product_Master!B:B) -> 7565.9667
A4: Avg Selling Price | B4: =_xlfn.XLOOKUP(B2, Product_Master!A:A, Product_Master!C:C) -> 12551.267
A5: Discount % | B5: 0.0256
A6: Discount Amount | B6: =B4*B5 -> 321.31243
A7: Discounted Price | B7: =B4-B6 -> 12229.954
A8: Profit Before Discount | B8: =B4-B3 -> 4985.3
A9: Profit After Discount | B9: =B7-B3 -> 4663.9876
A12: Select a product and enter a discount percentage to evaluate the impact on profitability.

Sheet Pivot_Table
A1: Revenue by Product | G1: Profit by Product
A2: Row Labels | B2: Sum of Revenue | G2: Row Labels | H2: Sum of Profit
A3: Vitamin C Serum | B3: 3845198 | G3: Vitamin C Serum | H3: 1315511
A4: Retinol Serum | B4: 2131792 | G4: Hydrating Cream | H4: 756596
A5: Toner | B5: 2065190 | G5: Retinol Serum | H5: 734434
A6: Hydrating Cream | B6: 1956929 | G6: Body Scrub | H6: 648885
A7: Body Scrub | B7: 1937617 | G7: Night Cream | H7: 598764
A8: Lip Balm | B8: 1666053 | G8: Toner | H8: 578304
A9: Hyaluronic Acid Serum | B9: 1651656 | G9: Lip Scrub | H9: 572653
A10: Night Cream | B10: 1599345 | G10: Hyaluronic Acid Serum | H10: 569014
A11: Sunscreen Spf50 | B11: 1555526 | G11: Lip Balm | H11: 564561
A12: Lip Scrub | B12: 1460662 | G12: Face Wash | H12: 550040
A13: Deep Clean Cleanser | B13: 1436405 | G13: Sunscreen Spf50 | H13: 499118
A14: Niacinamide Serum | B14: 1344943 | G14: Niacinamide Serum | H14: 462783
... A20: Grand Total | B20: 28082936 | G20: Grand Total | H20: 9766653
A24: Revenue by Category | G24: Revenue by Sales Channel
A25: Row Labels | B25: Sum of Revenue | G25: Row Labels | H25: Sum of Revenue
A26: Serum | B26: 8973589 | G26: Instagram | H26: 7318188
A27: Other | B27: 8028694 | G27: Retail | H27: 7258247
A28: Moisturizer | B28: 4557133 | G28: Website | H28: 7114629
A29: Cleanser | B29: 4006027 | G29: WhatsApp | H29: 6391872
A30: Protection | B30: 2517493 | G30: Grand Total | H30: 28082936
A31: Grand Total | B31: 28082936
A39: Revenue by Country | G39: Quantity Sold by Age Group
A40: Row Labels | B40: Sum of Revenue | G40: Row Labels | H40: Sum of Quantity_Sold
A41: Nigeria | B41: 16290076 | G41: Teen | H41: 883
A42: South Africa | B42: 4732455 | G42: Adult | H42: 689
A43: Kenya | B43: 3581996 | G43: Young Adult | H43: 676
A44: Ghana | B44: 3478409 | G44: Grand Total | H44: 2248
A45: Grand Total | B45: 28082936
G54: KPI 1
A55: Revenue Over Time | G55: Sum of Revenue
A56: Row Labels | B56: Sum of Revenue | G56: 28082936
A57: Jan | B57: 2919448
A58: Feb | B58: 2716210 | G58: KPI 2
A59: Mar | B59: 3246292 | G59: Sum of Profit
A60: Apr | B60: 3356835 | G60: 9766653
A61: May | B61: 2982542
A62: Jun | B62: 3306122 | G62: KPI 3
A63: Jul | B63: 1976673 | G63: Sum of Quantity_Sold
A64: Aug | B64: 1434225 | G64: 2248
A65: Sep | B65: 1257561
A66: Oct | B66: 1539463 | G66: KPI 4
A67: Nov | B67: 1772345 | G67: Average of Discount_Percent
A68: Dec | B68: 1575220 | G68: 0.04308
A69: Grand Total | B69: 28082936
